{
  "formatVersion": 1,
  "database": {
    "version": 1,
    "identityHash": "026fa6ebf7508e9d513f5b6894f2d75e",
    "entities": [
      {
        "tableName": "Cast",
        "createSql": "CREATE TABLE IF NOT EXISTS `${TABLE_NAME}` (`imdbCode` TEXT NOT NULL, `characterName` TEXT, `name` TEXT, `urlSmallImage` TEXT, PRIMARY KEY(`imdbCode`))",
        "fields": [
          {
            "fieldPath": "imdbCode",
            "columnName": "imdbCode",
            "affinity": "TEXT",
            "notNull": true
          },
          {
            "fieldPath": "characterName",
            "columnName": "characterName",
            "affinity": "TEXT",
            "notNull": false
          },
          {
            "fieldPath": "name",
            "columnName": "name",
            "affinity": "TEXT",
            "notNull": false
          },
          {
            "fieldPath": "urlSmallImage",
            "columnName": "urlSmallImage",
            "affinity": "TEXT",
            "notNull": false
          }
        ],
        "primaryKey": {
          "autoGenerate": false,
          "columnNames": [
            "imdbCode"
          ]
        },
        "indices": [],
        "foreignKeys": []
      },
      {
        "tableName": "Movie",
        "createSql": "CREATE TABLE IF NOT EXISTS `${TABLE_NAME}` (`id` INTEGER NOT NULL, `backgroundImage` TEXT, `backgroundImageOriginal` TEXT, `dateUploaded` TEXT, `dateUploadedUnix` INTEGER, `descriptionFull` TEXT, `descriptionIntro` TEXT, `downloadCount` INTEGER, `genres` TEXT, `imdbCode` TEXT, `language` TEXT, `largeCoverImage` TEXT, `largeScreenshotImage1` TEXT, `largeScreenshotImage2` TEXT, `largeScreenshotImage3` TEXT, `likeCount` INTEGER, `mediumCoverImage` TEXT, `mediumScreenshotImage1` TEXT, `mediumScreenshotImage2` TEXT, `mediumScreenshotImage3` TEXT, `mpaRating` TEXT, `rating` REAL, `runtime` INTEGER, `slug` TEXT, `smallCoverImage` TEXT, `state` TEXT, `summary` TEXT, `synopsis` TEXT, `title` TEXT, `titleEnglish` TEXT, `titleLong` TEXT, `url` TEXT, `year` INTEGER, `ytTrailerCode` TEXT, PRIMARY KEY(`id`))",
        "fields": [
          {
            "fieldPath": "id",
            "columnName": "id",
            "affinity": "INTEGER",
            "notNull": true
          },
          {
            "fieldPath": "backgroundImage",
            "columnName": "backgroundImage",
            "affinity": "TEXT",
            "notNull": false
          },
          {
            "fieldPath": "backgroundImageOriginal",
            "columnName": "backgroundImageOriginal",
            "affinity": "TEXT",
            "notNull": false
          },
          {
            "fieldPath": "dateUploaded",
            "columnName": "dateUploaded",
            "affinity": "TEXT",
            "notNull": false
          },
          {
            "fieldPath": "dateUploadedUnix",
            "columnName": "dateUploadedUnix",
            "affinity": "INTEGER",
            "notNull": false
          },
          {
            "fieldPath": "descriptionFull",
            "columnName": "descriptionFull",
            "affinity": "TEXT",
            "notNull": false
          },
          {
            "fieldPath": "descriptionIntro",
            "columnName": "descriptionIntro",
            "affinity": "TEXT",
            "notNull": false
          },
          {
            "fieldPath": "downloadCount",
            "columnName": "downloadCount",
            "affinity": "INTEGER",
            "notNull": false
          },
          {
            "fieldPath": "genres",
            "columnName": "genres",
            "affinity": "TEXT",
            "notNull": false
          },
          {
            "fieldPath": "imdbCode",
            "columnName": "imdbCode",
            "affinity": "TEXT",
            "notNull": false
          },
          {
            "fieldPath": "language",
            "columnName": "language",
            "affinity": "TEXT",
            "notNull": false
          },
          {
            "fieldPath": "largeCoverImage",
            "columnName": "largeCoverImage",
            "affinity": "TEXT",
            "notNull": false
          },
          {
            "fieldPath": "largeScreenshotImage1",
            "columnName": "largeScreenshotImage1",
            "affinity": "TEXT",
            "notNull": false
          },
          {
            "fieldPath": "largeScreenshotImage2",
            "columnName": "largeScreenshotImage2",
            "affinity": "TEXT",
            "notNull": false
          },
          {
            "fieldPath": "largeScreenshotImage3",
            "columnName": "largeScreenshotImage3",
            "affinity": "TEXT",
            "notNull": false
          },
          {
            "fieldPath": "likeCount",
            "columnName": "likeCount",
            "affinity": "INTEGER",
            "notNull": false
          },
          {
            "fieldPath": "mediumCoverImage",
            "columnName": "mediumCoverImage",
            "affinity": "TEXT",
            "notNull": false
          },
          {
            "fieldPath": "mediumScreenshotImage1",
            "columnName": "mediumScreenshotImage1",
            "affinity": "TEXT",
            "notNull": false
          },
          {
            "fieldPath": "mediumScreenshotImage2",
            "columnName": "mediumScreenshotImage2",
            "affinity": "TEXT",
            "notNull": false
          },
          {
            "fieldPath": "mediumScreenshotImage3",
            "columnName": "mediumScreenshotImage3",
            "affinity": "TEXT",
            "notNull": false
          },
          {
            "fieldPath": "mpaRating",
            "columnName": "mpaRating",
            "affinity": "TEXT",
            "notNull": false
          },
          {
            "fieldPath": "rating",
            "columnName": "rating",
            "affinity": "REAL",
            "notNull": false
          },
          {
            "fieldPath": "runtime",
            "columnName": "runtime",
            "affinity": "INTEGER",
            "notNull": false
          },
          {
            "fieldPath": "slug",
            "columnName": "slug",
            "affinity": "TEXT",
            "notNull": false
          },
          {
            "fieldPath": "smallCoverImage",
            "columnName": "smallCoverImage",
            "affinity": "TEXT",
            "notNull": false
          },
          {
            "fieldPath": "state",
            "columnName": "state",
            "affinity": "TEXT",
            "notNull": false
          },
          {
            "fieldPath": "summary",
            "columnName": "summary",
            "affinity": "TEXT",
            "notNull": false
          },
          {
            "fieldPath": "synopsis",
            "columnName": "synopsis",
            "affinity": "TEXT",
            "notNull": false
          },
          {
            "fieldPath": "title",
            "columnName": "title",
            "affinity": "TEXT",
            "notNull": false
          },
          {
            "fieldPath": "titleEnglish",
            "columnName": "titleEnglish",
            "affinity": "TEXT",
            "notNull": false
          },
          {
            "fieldPath": "titleLong",
            "columnName": "titleLong",
            "affinity": "TEXT",
            "notNull": false
          },
          {
            "fieldPath": "url",
            "columnName": "url",
            "affinity": "TEXT",
            "notNull": false
          },
          {
            "fieldPath": "year",
            "columnName": "year",
            "affinity": "INTEGER",
            "notNull": false
          },
          {
            "fieldPath": "ytTrailerCode",
            "columnName": "ytTrailerCode",
            "affinity": "TEXT",
            "notNull": false
          }
        ],
        "primaryKey": {
          "autoGenerate": false,
          "columnNames": [
            "id"
          ]
        },
        "indices": [],
        "foreignKeys": []
      },
      {
        "tableName": "Torrent",
        "createSql": "CREATE TABLE IF NOT EXISTS `${TABLE_NAME}` (`hash` TEXT NOT NULL, `dateUploaded` TEXT, `dateUploadedUnix` INTEGER, `peers` INTEGER, `quality` TEXT, `seeds` INTEGER, `size` TEXT, `sizeBytes` INTEGER, `type` TEXT, `url` TEXT, PRIMARY KEY(`hash`))",
        "fields": [
          {
            "fieldPath": "hash",
            "columnName": "hash",
            "affinity": "TEXT",
            "notNull": true
          },
          {
            "fieldPath": "dateUploaded",
            "columnName": "dateUploaded",
            "affinity": "TEXT",
            "notNull": false
          },
          {
            "fieldPath": "dateUploadedUnix",
            "columnName": "dateUploadedUnix",
            "affinity": "INTEGER",
            "notNull": false
          },
          {
            "fieldPath": "peers",
            "columnName": "peers",
            "affinity": "INTEGER",
            "notNull": false
          },
          {
            "fieldPath": "quality",
            "columnName": "quality",
            "affinity": "TEXT",
            "notNull": false
          },
          {
            "fieldPath": "seeds",
            "columnName": "seeds",
            "affinity": "INTEGER",
            "notNull": false
          },
          {
            "fieldPath": "size",
            "columnName": "size",
            "affinity": "TEXT",
            "notNull": false
          },
          {
            "fieldPath": "sizeBytes",
            "columnName": "sizeBytes",
            "affinity": "INTEGER",
            "notNull": false
          },
          {
            "fieldPath": "type",
            "columnName": "type",
            "affinity": "TEXT",
            "notNull": false
          },
          {
            "fieldPath": "url",
            "columnName": "url",
            "affinity": "TEXT",
            "notNull": false
          }
        ],
        "primaryKey": {
          "autoGenerate": false,
          "columnNames": [
            "hash"
          ]
        },
        "indices": [],
        "foreignKeys": []
      }
    ],
    "views": [],
    "setupQueries": [
      "CREATE TABLE IF NOT EXISTS room_master_table (id INTEGER PRIMARY KEY,identity_hash TEXT)",
      "INSERT OR REPLACE INTO room_master_table (id,identity_hash) VALUES(42, '026fa6ebf7508e9d513f5b6894f2d75e')"
    ]
  }
}